base56/.gitignore
base56/__init__.py
base56/_version.py
base56/alphabet.py
base56/encoding.py
base56/version.py
base56/test/conftest.py
base56/test/test_alphabet.py
base56/test/test_ambiguity.py
base56/test/test_compatibility.py
base56/test/test_encoding.py
base56/test/test_with_doctest.py
base56-0.1.1.dist-info/METADATA
base56-0.1.1.dist-info/WHEEL
base56-0.1.1.dist-info/licenses/LICENSE
base56-0.1.1.dist-info/RECORD
