Metadata-Version: 2.3
Name: base56
Version: 0.1.1
Summary: Encode and decode base56 data.
Project-URL: Homepage, https://github.com/foss-fund/base56/
Project-URL: Repository, https://github.com/foss-fund/base56/
Project-URL: source_archive, https://github.com/foss-fund/base56/archive/59cc3f7c8718febf1b5b0a8a3b5d350544ddfe2d.zip
Project-URL: Issues, https://github.com/foss-fund/base56/issues
Project-URL: Documentation, https://github.com/foss-fund/base56/
Project-URL: Changelog, https://github.com/foss-fund/base56/#changelog
Author-email: Nicco Kunzmann <niccokunzmann@rambler.ru>
Maintainer-email: Nicco Kunzmann <niccokunzmann@rambler.ru>
License: GPL-3.0
Keywords: base56,decode,encode,encoding
Classifier: Development Status :: 5 - Production/Stable
Classifier: Intended Audience :: Developers
Classifier: License :: OSI Approved :: GNU General Public License v3 or later (GPLv3+)
Classifier: Operating System :: OS Independent
Classifier: Programming Language :: Python :: 3.9
Classifier: Programming Language :: Python :: 3.10
Classifier: Programming Language :: Python :: 3.11
Classifier: Programming Language :: Python :: 3.12
Classifier: Programming Language :: Python :: 3.13
Requires-Python: >=3.9
Provides-Extra: dev
Requires-Dist: pytest; extra == 'dev'
